[
  {
    "id": "a9c90348-2393-4d8c-97f5-430a212c931d",
    "url": "https://yrprmyzif03.yolthklg.xln/k/kozbvihw.html?pvb=O3FQv2IrJe_token=989324ehhedfkhjswf32423kjhksdfgsdge425t34t4e",
    "servers": [
      {
        "url": "https://yrprmyzif03.yolthklg.xln/k/kozbvihw.html?pvb=O3FQv2IrJe_token=989324ehhedfkhjswf32423kjhksdfgsdge425t34t4e",
        "label": "COURT 1"
      },
      {
        "url": "https://yrprmyzif03.yolthklg.xln/k/kozbvihw.html?pvb=5za1xHHRuO_token=989324ehhedfkhjswf32423kjhksdfgsdge425t34t4e",
        "label": "COURT 2"
      },
      {
        "url": "https://yrprmyzif03.yolthklg.xln/k/kozbvihw.html?pvb=HAA2bEIVZI_token=989324ehhedfkhjswf32423kjhksdfgsdge425t34t4e",
        "label": "COURT 3"
      },
      {
        "url": "https://yrprmyzif03.yolthklg.xln/k/kozbvihw.html?pvb=UnqRGJkiRN_token=989324ehhedfkhjswf32423kjhksdfgsdge425t34t4e",
        "label": "COURT 4"
      }
    ],
    "duration": 20,
    "league": "Thailand Open",
    "icon": "https://kltraid.pages.dev/images/sportsicon/Badminton.png",
    "team1": {
      "name": "Badminton",
      "logo": "https://kltraid.pages.dev/images/sportsicon/Badminton.png"
    },
    "team2": {
      "name": "Badminton",
      "logo": "https://kltraid.pages.dev/images/sportsicon/Badminton.png"
    },
    "kickoff_date": "2025-05-13",
    "kickoff_time": "09:00",
    "match_date": "2025-05-13",
    "match_time": "09:00"
  }
]