[
  {
    "id": "27372188-3d37-4a38-a601-8523963eac14",
    "servers": [
      {
        "key": "VeFig6iPt0",
        "url": "https://bikinbaru96.blogspot.com/p/playermpd.html?channel=ad2",
        "label": "SD [IOS]"
      },
      {
        "key": "QhvLx7e0NV",
        "url": "",
        "label": ""
      },
      {
        "key": "6dHhPzelgX",
        "url": "",
        "label": ""
      }
    ]
  },
  {
    "id": "d180ad75-252c-475c-bd1e-f063524850ec",
    "servers": [
      {
        "key": "lGGaLaQS6X",
        "url": "https://bikinbaru96.blogspot.com/p/playermpd.html?channel=ad1",
        "label": "HD AUTO"
      },
      {
        "key": "qEVT70N52Q",
        "url": "https://bikinbaru96.blogspot.com/p/playermpd.html?channel=beinau3",
        "label": "HD AUTO"
      },
      {
        "key": "V57Epu88Ut",
        "url": "",
        "label": ""
      },
      {
        "key": "LEY5n6sSvZ",
        "url": "",
        "label": ""
      },
      {
        "key": "aA34TYdjUN",
        "url": "",
        "label": ""
      },
      {
        "key": "JrRHLtykoc",
        "url": "",
        "label": ""
      }
    ]
  },
  {
    "id": "689f27a0-c6e7-490a-952f-324db24e81d8",
    "servers": [
      {
        "key": "En4r7PpgBq",
        "url": "https://bikinbaru96.blogspot.com/p/playermpd.html?channel=beinid1",
        "label": "HD AUTO"
      },
      {
        "key": "fnCMEFsW48",
        "url": "https://goalstreamz.com/f1streams/streams/",
        "label": "SD [IOS]"
      }
    ]
  },
  {
    "id": "cc605cda-4d82-476d-923a-c99f2191029e",
    "servers": [
      {
        "key": "BqtGLO8RCe",
        "url": "https://bikinbaru96.blogspot.com/p/playermpd.html?channel=tnt2",
        "label": "HD AUTO"
      },
      {
        "key": "tbhfh828Xs",
        "url": "https://bikinbaru96.blogspot.com/p/playermpd.html?channel=spoph1",
        "label": "HD AUTO"
      },
      {
        "key": "MNpnnY38VO",
        "url": "https://livetvkilatlive.applecdnstore.com/livetv/2024/UK_TNT_SPORTS_2/index.m3u8",
        "label": "SD [IOS]"
      }
    ]
  },
  {
    "id": "594da826-1ad4-45d3-99bc-7d8cce4f812b",
    "servers": [
      {
        "key": "wF1iYArrcE",
        "url": "https://3be4be19ef6d73cd744383f2da36c93f.v.smtcdns.net/play.cbalive.weibisai.com/live/3895262576711061_AiSD.m3u8?txSecret=b70a81dce8440a2165ab5d039d0b2fad&txTime=682A9EB0",
        "label": "COURT 1"
      },
      {
        "key": "M4rLS4YRDD",
        "url": "https://thapcam.elutuna.workers.dev/NNixORr4dHm8mzV0-UsYgA/Fv2lucGIbhPi2caWYvF5Lg/1747566270215/live/longSD/playlist.m3u8",
        "label": "COURT 1"
      }
    ]
  },
  {
    "id": "cffb21c6-4930-43fc-9888-903782df32ae",
    "servers": [
      {
        "key": "KkhltDX3nL",
        "url": "https://sport.inplaynet.tech/livestream.html?src=aHR0cHM6Ly9zbWQuc3BvcnRwbGF5ZXIuaW8vZW1iZWQucGhwLz9tYXRjaF9pZD0xMjY4MjIxMyZzaz0xYzlhYzAxJnR5cGU9cw==",
        "label": "SD [IOS]"
      },
      {
        "key": "xxMMLxXFTq",
        "url": "https://live2.jiatianxiazhuangshi.com/live/57436775_74edaf22cf7ecfbc90af758803afaea0_nsd.m3u8",
        "label": "ANDROID/PC"
      }
    ]
  },
  {
    "id": "2440ff92-9ccb-4965-aa72-1f5156609d44",
    "servers": [
      {
        "key": "bUZ6zc8VaB",
        "url": "https://sport.inplaynet.tech/livestream.html?src=aHR0cHM6Ly9zbWQuc3BvcnRwbGF5ZXIuaW8vZW1iZWQucGhwLz9tYXRjaF9pZD0xMjY4MjIxNCZzaz0xYzlhYzAxJnR5cGU9cw==",
        "label": "SD [IOS]"
      },
      {
        "key": "b6lMt4HSXB",
        "url": "https://live1.jiatianxiazhuangshi.com/live/57436773_ae2475ebe8b1618a22f4c27d4be3ee3f_nsd.m3u8",
        "label": "ANDROID/PC"
      }
    ]
  },
  {
    "id": "0f869666-c813-4e44-b3ad-8969e2e38473",
    "servers": [
      {
        "key": "JHHYskKQ9W",
        "url": "https://sport.inplaynet.tech/livestream.html?src=aHR0cHM6Ly9zbWQuc3BvcnRwbGF5ZXIuaW8vZW1iZWQucGhwLz9tYXRjaF9pZD0xMjY4MjE5NiZzaz0xYzlhYzAxJnR5cGU9cw==",
        "label": "SD [IOS]"
      },
      {
        "key": "CPxHr5HcZt",
        "url": "https://live1.jiatianxiazhuangshi.com/live/52325141_34d793e6c5f7aa1dd72c6c9828d470ff_nsd.m3u8",
        "label": "ANDROID/PC"
      },
      {
        "key": "3D2V0pBTEf",
        "url": "https://vt-osoi7r4b.sportcdn.live/live/live-1-4184682-0.m3u8?txSecret=21da019f80f3a88304067f89f99a8975&txTime=6829b71b",
        "label": "SD [IOS]"
      }
    ]
  },
  {
    "id": "8fe2959d-3c05-49b6-be69-e298566a0bbe",
    "servers": [
      {
        "key": "KQW46WUfNe",
        "url": "https://sport.inplaynet.tech/livestream.html?src=aHR0cHM6Ly9zbWQuc3BvcnRwbGF5ZXIuaW8vZW1iZWQucGhwLz9tYXRjaF9pZD0xMjY2MjI5MiZzaz0xYzlhYzAxJnR5cGU9cw==",
        "label": "SD [IOS]"
      },
      {
        "key": "IB4apz7Fxx",
        "url": "https://live2.jiatianxiazhuangshi.com/live/57130723_5a36af80f7ce42acacf4cfe5c1804bbb_nsd.m3u8",
        "label": "ANDROID/PC"
      }
    ]
  },
  {
    "id": "4c93e0a1-d37d-4137-853b-eb5cfeff3804",
    "servers": [
      {
        "key": "KO7xyIqF3H",
        "url": "https://sport.inplaynet.tech/livestream.html?src=aHR0cHM6Ly9zbWQuc3BvcnRwbGF5ZXIuaW8vZW1iZWQucGhwLz9tYXRjaF9pZD0xMjY2MjI5MyZzaz0xYzlhYzAxJnR5cGU9cw==",
        "label": "SD [IOS]"
      },
      {
        "key": "HRxLzbIndh",
        "url": "https://live3.jiatianxiazhuangshi.com/live/57130725_d8353cf0bf83105333dce75f09b56a76_nsd.m3u8",
        "label": "ANDROID/PC"
      }
    ]
  },
  {
    "id": "26dab815-5b6e-4289-91de-a302b4c9248f",
    "servers": [
      {
        "key": "U6E8VnVw5s",
        "url": "https://sport.inplaynet.tech/livestream.html?src=aHR0cHM6Ly9zbWQuc3BvcnRwbGF5ZXIuaW8vZW1iZWQucGhwLz9tYXRjaF9pZD0xMjY4MjE5NyZzaz0xYzlhYzAxJnR5cGU9cw==",
        "label": "SD [IOS]"
      },
      {
        "key": "46sk87wDlC",
        "url": "https://live.jiatianxiazhuangshi.com/live/52325143_729b2e3b7c699ec6fd46307c5245b647_nsd.m3u8",
        "label": "ANDROID/PC"
      }
    ]
  },
  {
    "id": "9a197e2b-bc58-4311-9cc6-27f8650359f3",
    "servers": [
      {
        "key": "e1IrDuOdZQ",
        "url": "https://sport.inplaynet.tech/livestream.html?src=aHR0cHM6Ly9zbWQuc3BvcnRwbGF5ZXIuaW8vZW1iZWQucGhwLz9tYXRjaF9pZD0xMjY2MjI5NCZzaz0xYzlhYzAxJnR5cGU9cw==",
        "label": "SD [IOS]"
      },
      {
        "key": "FJLcL4fbkJ",
        "url": "https://live.jiatianxiazhuangshi.com/live/57130727_219cef535a79c3bfd19174e71f820488_nsd.m3u8",
        "label": "ANDROID/PC"
      }
    ]
  },
  {
    "id": "c83960ff-76fc-4f3e-b42c-cd1e07cc4cfa",
    "servers": [
      {
        "key": "4cbkytnBhN",
        "url": "https://bikinbaru96.blogspot.com/p/playermpd.html?channel=usacwest",
        "label": "HD AUTO"
      },
      {
        "key": "SU7EYjQWAU",
        "url": "https://bikinbaru96.blogspot.com/p/playermpd.html?channel=tnt1",
        "label": "HD AUTO"
      },
      {
        "key": "cumv9AK97y",
        "url": "https://sport.inplaynet.tech/livestream.html?src=aHR0cHM6Ly9zbWQuc3BvcnRwbGF5ZXIuaW8vZW1iZWQucGhwLz9tYXRjaF9pZD0xMjY1ODkyMyZzaz0xYzlhYzAxJnR5cGU9cw==",
        "label": "SD [IOS]"
      },
      {
        "key": "romVBNyTqx",
        "url": "https://rr4---sn-8pxuuxa-onon.applecdnstore.com/livetv/2024/UK_TNT_SPORTS_1/index.m3u8",
        "label": "SD [IOS]"
      },
      {
        "key": "tLlUWgjQUM",
        "url": "https://lc.elutuna.workers.dev/409/playlist.m3u8",
        "label": "SD [IOS]"
      },
      {
        "key": "mLfhOOiuST",
        "url": "https://hipaf6u2j3pwygg.nice-flower.store/v3/director/VE1OTRlYjAwNjVkMTdjLTdlZmItNmYwNC1iODZiLTBjMDBiMjcz/master.m3u8?md5=H94Jdc36-0D7d9wuE17-QA&expires=1747609276",
        "label": "HD [IOS]"
      }
    ]
  },
  {
    "id": "cf26f1ea-a032-461e-aa36-7012a5fe2bde",
    "servers": [
      {
        "key": "GfWWwntWAv",
        "url": "https://sport.inplaynet.tech/livestream.html?src=aHR0cHM6Ly9zbWQuc3BvcnRwbGF5ZXIuaW8vZW1iZWQucGhwLz9tYXRjaF9pZD0xMjY4MjE5OCZzaz0xYzlhYzAxJnR5cGU9cw==",
        "label": "SD [IOS]"
      },
      {
        "key": "Sxg9drLZX4",
        "url": "https://vt-osoi7r4b.sportcdn.live/live/live-1-4184684-0.m3u8?txSecret=98aa1d441802debfb3bec752ff790da4&txTime=682a045e",
        "label": "SD [IOS]"
      },
      {
        "key": "Nx5elSSWVp",
        "url": "https://live.jiatianxiazhuangshi.com/live/52325145_c748b9c3f22437a76654a698e3245eff_nsd.m3u8",
        "label": "ANDROID/PC"
      }
    ]
  },
  {
    "id": "eedf0361-3d72-487b-bba5-f311b9a7a88a",
    "servers": [
      {
        "key": "Dfmpt6fBO2",
        "url": "https://sc.elutuna.workers.dev/326/chunklist.m3u8",
        "label": "SD [IOS]"
      },
      {
        "key": "TdoTgxNxGP",
        "url": "",
        "label": ""
      }
    ]
  },
  {
    "id": "45b7eb59-8678-409d-a267-7dea58470039",
    "servers": [
      {
        "key": "vntP9ETiAh",
        "url": "https://live3.jiatianxiazhuangshi.com/live/56376103_4a6c95155a0aed4cb06226552d715888_nsd.m3u8",
        "label": "ANDROID/PC"
      },
      {
        "key": "ehpSPXveQm",
        "url": "https://vt-osoi7r4b.sportcdn.live/live/live-1-4321341-2.m3u8?txSecret=fe6130b3475084157cf2584d2fe8a4ef&txTime=682a045e",
        "label": "SD [IOS]"
      },
      {
        "key": "armvvZrMkt",
        "url": "",
        "label": ""
      }
    ]
  },
  {
    "id": "4b9debf5-46fd-4e67-8045-dc7e1732aaf0",
    "servers": [
      {
        "key": "xhtpjW4YNq",
        "url": "https://bikinbaru96.blogspot.com/p/playermpd.html?channel=usacwest",
        "label": "HD AUTO"
      },
      {
        "key": "M8CKgbbh6p",
        "url": "https://bikinbaru96.blogspot.com/p/playermpd.html?channel=univ",
        "label": "HD AUTO"
      },
      {
        "key": "bndR5lfYuW",
        "url": "https://sport.inplaynet.tech/livestream.html?src=aHR0cHM6Ly9zbWQuc3BvcnRwbGF5ZXIuaW8vZW1iZWQucGhwLz9tYXRjaF9pZD0xMjY1ODkyNiZzaz0xYzlhYzAxJnR5cGU9cw==",
        "label": "SD [IOS]"
      },
      {
        "key": "bcI390VvCt",
        "url": "https://rr4---sn-8pxuuxa-onon.applecdnstore.com/livetv/2024/UK_SKY_SPORTS_MAIN_EVENT/index.m3u8",
        "label": "SD [IOS]"
      },
      {
        "key": "Oz341113b1",
        "url": "https://kc.elutuna.workers.dev/209/playlist.m3u8",
        "label": "SD [IOS]"
      },
      {
        "key": "7GOk2tjxDZ",
        "url": "",
        "label": ""
      }
    ]
  },
  {
    "id": "1e78e2d0-068b-413b-be97-217e8d1fa485",
    "servers": [
      {
        "key": "hXpSiJIqNh",
        "url": "https://sport.inplaynet.tech/livestream.html?src=aHR0cHM6Ly9zbWQuc3BvcnRwbGF5ZXIuaW8vZW1iZWQucGhwLz9tYXRjaF9pZD0xMjY1ODkzNCZzaz0xYzlhYzAxJnR5cGU9cw==",
        "label": "SD [IOS]"
      },
      {
        "key": "mdB7yCVi0S",
        "url": "https://kc.elutuna.workers.dev/203/playlist.m3u8",
        "label": "SD [IOS]"
      },
      {
        "key": "seAdrciuL6",
        "url": "",
        "label": ""
      },
      {
        "key": "aZar3ddCyA",
        "url": "",
        "label": ""
      },
      {
        "key": "9I8Iotvy7I",
        "url": "",
        "label": ""
      }
    ]
  },
  {
    "id": "1668bb7d-a96a-4aa5-9efa-fb70a5574fe0",
    "servers": [
      {
        "key": "HhmatLiYMQ",
        "url": "https://sport.inplaynet.tech/livestream.html?src=aHR0cHM6Ly9zbWQuc3BvcnRwbGF5ZXIuaW8vZW1iZWQucGhwLz9tYXRjaF9pZD0xMjY1ODkzNiZzaz0xYzlhYzAxJnR5cGU9cw==",
        "label": "SD [IOS]"
      },
      {
        "key": "SC7CUyGJHf",
        "url": "https://kc.elutuna.workers.dev/204/playlist.m3u8",
        "label": "SD [IOS]"
      },
      {
        "key": "RuDTTbv07I",
        "url": "",
        "label": ""
      },
      {
        "key": "BizfUaaDY1",
        "url": "",
        "label": ""
      },
      {
        "key": "vZneNzwmF2",
        "url": "",
        "label": ""
      }
    ]
  },
  {
    "id": "6baf9fa6-e346-46c5-be67-1ea19c9485e3",
    "servers": [
      {
        "key": "NghS2j4baZ",
        "url": "https://bikinbaru96.blogspot.com/p/playermpd.html?channel=usacwest",
        "label": "HD AUTO"
      },
      {
        "key": "suihcJT46T",
        "url": "https://bikinbaru96.blogspot.com/p/playermpd.html?channel=tel",
        "label": "HD AUTO"
      },
      {
        "key": "UEEL4raD9t",
        "url": "https://sport.inplaynet.tech/livestream.html?src=aHR0cHM6Ly9zbWQuc3BvcnRwbGF5ZXIuaW8vZW1iZWQucGhwLz9tYXRjaF9pZD0xMjY1ODkzNyZzaz0xYzlhYzAxJnR5cGU9cw==",
        "label": "SD [IOS]"
      },
      {
        "key": "VUNLZgZio7",
        "url": "https://rr4---sn-8pxuuxa-onon.applecdnstore.com/livetv/2024/UK_SKY_SPORTS_MAIN_EVENT/index.m3u8",
        "label": "SD [IOS]"
      },
      {
        "key": "SwVzbe8djy",
        "url": "https://kc.elutuna.workers.dev/209/playlist.m3u8",
        "label": "SD [IOS]"
      },
      {
        "key": "YFARf2lZAW",
        "url": "",
        "label": ""
      }
    ]
  },
  {
    "id": "bf824d6c-e5f8-409a-8fcb-64aaa11793eb",
    "servers": [
      {
        "key": "ef8bBmq4Ch",
        "url": "https://sport.inplaynet.tech/livestream.html?src=aHR0cHM6Ly9zbWQuc3BvcnRwbGF5ZXIuaW8vZW1iZWQucGhwLz9tYXRjaF9pZD0xMjY2MjQxNSZzaz0xYzlhYzAxJnR5cGU9cw==",
        "label": "SD [IOS]"
      },
      {
        "key": "a0HvREcNiu",
        "url": "https://sport.inplaynet.tech/livestream.html?src=aHR0cHM6Ly9zbWQuc3BvcnRwbGF5ZXIuaW8vZW1iZWQucGhwLz9tYXRjaF9pZD0xMjY2MjQxNSZzaz0xYzlhYzAxJnR5cGU9cw==",
        "label": "SD [IOS]"
      },
      {
        "key": "7xFpZ62fev",
        "url": "https://live.jiatianxiazhuangshi.com/live/51472441_c2e79b8a5f29c8e4ebcfb0805216104c_nsd.m3u8",
        "label": "ANDROID/PC"
      }
    ]
  },
  {
    "id": "bce387f3-0f30-462c-90d7-955c20f347b5",
    "servers": [
      {
        "key": "KfMZqe0w39",
        "url": "https://sport.inplaynet.tech/livestream.html?src=aHR0cHM6Ly9zbWQuc3BvcnRwbGF5ZXIuaW8vZW1iZWQucGhwLz9tYXRjaF9pZD0xMjY2MjQyMCZzaz0xYzlhYzAxJnR5cGU9cw==",
        "label": "SD [IOS]"
      },
      {
        "key": "qQcIK13SX8",
        "url": "https://sport.inplaynet.tech/livestream.html?src=aHR0cHM6Ly9zbWQuc3BvcnRwbGF5ZXIuaW8vZW1iZWQucGhwLz9tYXRjaF9pZD0xMjY2MjQyMCZzaz0xYzlhYzAxJnR5cGU9cw==",
        "label": "SD [IOS]"
      },
      {
        "key": "COOJMIBUcp",
        "url": "https://live5.jiatianxiazhuangshi.com/live/51472443_e577c142f0d17d733f3f91f8a190147d_nsd.m3u8",
        "label": "ANDROID/PC"
      }
    ]
  },
  {
    "id": "e2805a85-e946-48e8-89b8-f38530f0b1c6",
    "servers": [
      {
        "key": "IBfJzdj1aC",
        "url": "https://sport.inplaynet.tech/livestream.html?src=aHR0cHM6Ly9zbWQuc3BvcnRwbGF5ZXIuaW8vZW1iZWQucGhwLz9tYXRjaF9pZD0xMjY4MTc3NyZzaz0xYzlhYzAxJnR5cGU9cw==",
        "label": "SD [IOS]"
      },
      {
        "key": "DLoUiuX3VQ",
        "url": "https://live.jiatianxiazhuangshi.com/live/59082463_f1cc956978dcd8d3d978adade933e677_nsd.m3u8",
        "label": "ANDROID/PC"
      },
      {
        "key": "Lr03ke258u",
        "url": "https://vt-osoi7r4b.sportcdn.live/live/live-1-4308680-0.m3u8?txSecret=0c7e9323543a6c80011e90c0de6b6679&txTime=682a3ca9",
        "label": "SD [IOS]"
      }
    ]
  },
  {
    "id": "4a94813a-3e33-47d0-8d8e-e6566c415def",
    "servers": [
      {
        "key": "niwZrZ5zT0",
        "url": "https://sport.inplaynet.tech/livestream.html?src=aHR0cHM6Ly9zbWQuc3BvcnRwbGF5ZXIuaW8vZW1iZWQucGhwLz9tYXRjaF9pZD0xMjY2MjI3MiZzaz0xYzlhYzAxJnR5cGU9cw==",
        "label": "SD [IOS]"
      },
      {
        "key": "58MRpAPpWu",
        "url": "https://live.jiatianxiazhuangshi.com/live/50868565_657d57c29e61a2501b3b6900b86b08bf_nsd.m3u8",
        "label": "ANDROID/PC"
      },
      {
        "key": "xpq3NxMF9F",
        "url": "https://vt-osoi7r4b.sportcdn.live/live/live-1-4141512-0.m3u8?txSecret=ad823a138d609d15898ed6a96cb39b30&txTime=682a0b66",
        "label": "SD [IOS]"
      }
    ]
  },
  {
    "id": "317fa399-ef12-490c-bd4d-b1247a6f4624",
    "servers": [
      {
        "key": "x9O0ueYXND",
        "url": "https://sport.inplaynet.tech/livestream.html?src=aHR0cHM6Ly9zbWQuc3BvcnRwbGF5ZXIuaW8vZW1iZWQucGhwLz9tYXRjaF9pZD0xMjY2MjI3MSZzaz0xYzlhYzAxJnR5cGU9cw==",
        "label": "SD [IOS]"
      },
      {
        "key": "E8FKFFNTWV",
        "url": "https://vt-osoi7r4b.sportcdn.live/live/live-1-4141513-0.m3u8?txSecret=fa877c3e61a1623c2688af33e6ce1e92&txTime=682a0b66",
        "label": "SD [IOS]"
      }
    ]
  },
  {
    "id": "7e6f3fdf-faf4-4341-a993-87146c18f2c0",
    "servers": [
      {
        "key": "Ca9aBvwQLn",
        "url": "https://live4.jiatianxiazhuangshi.com/live/50868569_cbf104fc6bb7e79e9f0b3d1e91bea0d3_nsd.m3u8",
        "label": "ANDROID/PC"
      },
      {
        "key": "v5GDLRNzYS",
        "url": "https://vt-osoi7r4b.sportcdn.live/live/live-1-4141517-0.m3u8?txSecret=e8ce50d0b075cf86bd9cf009e7fb0706&txTime=682a0b66",
        "label": "SD [IOS]"
      }
    ]
  },
  {
    "id": "cbe7e03d-aefe-4979-a6cc-cfaeeb490aac",
    "servers": [
      {
        "key": "KX50kCb0nY",
        "url": "https://live.jiatianxiazhuangshi.com/live/50868571_baf0ce7ce9a652c6939f846412b951b2_nsd.m3u8",
        "label": "ANDROID/PC"
      },
      {
        "key": "trWnJXXHP6",
        "url": "https://vt-osoi7r4b.sportcdn.live/live/live-1-4141515-0.m3u8?txSecret=c96913c53a48c2598120c1ed48bd5099&txTime=682a0b66",
        "label": "SD [IOS]"
      }
    ]
  },
  {
    "id": "834a1ead-6b59-4863-8b4f-75084814cdea",
    "servers": [
      {
        "key": "d7NQAxnjvT",
        "url": "https://live3.jiatianxiazhuangshi.com/live/50868573_f04f762bcd2e363bd88b07a79f2ccd6c_nsd.m3u8",
        "label": "ANDROID/PC"
      },
      {
        "key": "cz0zLQIMYE",
        "url": "https://vt-osoi7r4b.sportcdn.live/live/live-1-4141516-0.m3u8?txSecret=68b1f60e92d9a28a33d1265c0d0ebf20&txTime=682a0c1a",
        "label": "SD [IOS]"
      }
    ]
  },
  {
    "id": "f554cca8-ce54-42c5-86ec-e9ba2addba20",
    "servers": [
      {
        "key": "eUCKDHB8uN",
        "url": "https://live1.jiatianxiazhuangshi.com/live/50868575_7543b549f3e55284b57d0a161303b378_nsd.m3u8",
        "label": "ANDROID/PC"
      },
      {
        "key": "xZeaiIKX7A",
        "url": "https://vt-osoi7r4b.sportcdn.live/live/live-1-4141520-0.m3u8?txSecret=8fa68a04c4e73bcc52aa1de8152a7f3a&txTime=682a0bb6",
        "label": "SD [IOS]"
      }
    ]
  },
  {
    "id": "cd609c3a-35fa-447b-8bb1-9d022cf44bcb",
    "servers": [
      {
        "key": "MpUaXitN19",
        "url": "https://live.jiatianxiazhuangshi.com/live/50868577_ca89059da56f435e42f1c66a5bd45232_nsd.m3u8",
        "label": "ANDROID/PC"
      },
      {
        "key": "OfiFvPKwY9",
        "url": "https://vt-osoi7r4b.sportcdn.live/live/live-1-4141519-0.m3u8?txSecret=3abda1c8019d5884b06d5135045aeed6&txTime=682a0c1a",
        "label": "SD [IOS]"
      }
    ]
  },
  {
    "id": "6c3d347f-08f5-4d13-ac60-82a792a3c136",
    "servers": [
      {
        "key": "pvv51tPab9",
        "url": "https://sport.inplaynet.tech/livestream.html?src=aHR0cHM6Ly9zbWQuc3BvcnRwbGF5ZXIuaW8vZW1iZWQucGhwLz9tYXRjaF9pZD0xMjY2MjI4MCZzaz0xYzlhYzAxJnR5cGU9cw==",
        "label": "SD [IOS]"
      },
      {
        "key": "28q03age78",
        "url": "https://live2.jiatianxiazhuangshi.com/live/50868579_f0c3fa146c44f698f36fe2ff842fe4f6_nsd.m3u8",
        "label": "ANDROID/PC"
      }
    ]
  },
  {
    "id": "d2a0ff12-eadd-42f1-b414-e7fcdba24aea",
    "servers": [
      {
        "key": "hMW7WDSGty",
        "url": "https://sport.inplaynet.tech/livestream.html?src=aHR0cHM6Ly9zbWQuc3BvcnRwbGF5ZXIuaW8vZW1iZWQucGhwLz9tYXRjaF9pZD0xMjY2MjI3OCZzaz0xYzlhYzAxJnR5cGU9cw==",
        "label": "SD [IOS]"
      },
      {
        "key": "CYndbqF3Mg",
        "url": "https://live5.jiatianxiazhuangshi.com/live/50868581_b11c981096fbabf51fc08dd0f4778f46_nsd.m3u8",
        "label": "ANDROID/PC"
      }
    ]
  },
  {
    "id": "c35d4ee0-2443-4cf6-b5fb-132564ca15b2",
    "servers": [
      {
        "key": "FYJ5hvYtNT",
        "url": "https://bikinbaru96.blogspot.com/p/playermpd.html?channel=beinid1",
        "label": "HD AUTO"
      },
      {
        "key": "IcrwZAtx6i",
        "url": "https://bikinbaru96.blogspot.com/p/playermpd.html?channel=daznde1",
        "label": "HD AUTO"
      },
      {
        "key": "d9SZUzWByv",
        "url": "https://sport.inplaynet.tech/livestream.html?src=aHR0cHM6Ly9zbWQuc3BvcnRwbGF5ZXIuaW8vZW1iZWQucGhwLz9tYXRjaF9pZD0xMjY1ODk3MyZzaz0xYzlhYzAxJnR5cGU9cw==",
        "label": "SD [IOS]"
      },
      {
        "key": "r5AVcYNIof",
        "url": "https://rr4---sn-8pxuuxa-onon.applecdnstore.com/livetv/2024/live_event_espn_plus_17/index.m3u8",
        "label": "SD [IOS]"
      },
      {
        "key": "XUHS2IWAPj",
        "url": "https://kc.elutuna.workers.dev/211/playlist.m3u8",
        "label": "SD [IOS]"
      },
      {
        "key": "vU0GNTyOOt",
        "url": "",
        "label": ""
      }
    ]
  },
  {
    "id": "88f8a796-c44e-4b71-982b-83727131d41b",
    "servers": [
      {
        "key": "cT01hhcUvL",
        "url": "https://sport.inplaynet.tech/livestream.html?src=aHR0cHM6Ly9zbWQuc3BvcnRwbGF5ZXIuaW8vZW1iZWQucGhwLz9tYXRjaF9pZD0xMjY1OTAxNyZzaz0xYzlhYzAxJnR5cGU9cw==",
        "label": "SD [IOS]"
      },
      {
        "key": "ASfsIjA20g",
        "url": "https://rr4---sn-8pxuuxa-onon.applecdnstore.com/livetv/2024/live_event_espn_plus_27/index.m3u8",
        "label": "SD [IOS]"
      },
      {
        "key": "mi8ZC3Bqfq",
        "url": "",
        "label": ""
      }
    ]
  },
  {
    "id": "cffa05b1-843f-4dbe-bf4b-6b914be0c87f",
    "servers": [
      {
        "key": "EJH5av7xpM",
        "url": "https://sport.inplaynet.tech/livestream.html?src=aHR0cHM6Ly9zbWQuc3BvcnRwbGF5ZXIuaW8vZW1iZWQucGhwLz9tYXRjaF9pZD0xMjY1ODk3NyZzaz0xYzlhYzAxJnR5cGU9cw==",
        "label": "SD [IOS]"
      },
      {
        "key": "G7XYZGZSAr",
        "url": "https://rr4---sn-8pxuuxa-onon.applecdnstore.com/livetv/2024/live_event_espn_plus_21/index.m3u8",
        "label": "SD [IOS]"
      },
      {
        "key": "aOX1gkgM4B",
        "url": "",
        "label": ""
      }
    ]
  },
  {
    "id": "fcdf3b6c-ed66-4551-b01f-261083e6f7a6",
    "servers": [
      {
        "key": "t1STUtTiXG",
        "url": "https://sport.inplaynet.tech/livestream.html?src=aHR0cHM6Ly9zbWQuc3BvcnRwbGF5ZXIuaW8vZW1iZWQucGhwLz9tYXRjaF9pZD0xMjY1ODk5NSZzaz0xYzlhYzAxJnR5cGU9cw==",
        "label": "SD [IOS]"
      },
      {
        "key": "v6OS4tgHEQ",
        "url": "https://rr4---sn-8pxuuxa-onon.applecdnstore.com/livetv/2024/live_event_espn_plus_32/index.m3u8",
        "label": "SD [IOS]"
      },
      {
        "key": "kGKyw3lZJZ",
        "url": "",
        "label": ""
      }
    ]
  },
  {
    "id": "a0f2b450-ec01-4bd9-b183-5cf5f8c2c94d",
    "servers": [
      {
        "key": "Bh1iAs6AYM",
        "url": "https://sport.inplaynet.tech/livestream.html?src=aHR0cHM6Ly9zbWQuc3BvcnRwbGF5ZXIuaW8vZW1iZWQucGhwLz9tYXRjaF9pZD0xMjY1OTAwMCZzaz0xYzlhYzAxJnR5cGU9cw==",
        "label": "SD [IOS]"
      },
      {
        "key": "wO5DIrEkAn",
        "url": "https://rr4---sn-8pxuuxa-onon.applecdnstore.com/livetv/2024/live_event_espn_plus_29/index.m3u8",
        "label": "SD [IOS]"
      },
      {
        "key": "968qEtzTPU",
        "url": "",
        "label": ""
      }
    ]
  },
  {
    "id": "f45186bd-4e61-4a90-8973-232731c3154b",
    "servers": [
      {
        "key": "GcHi4y9XD1",
        "url": "https://bikinbaru96.blogspot.com/p/playermpd.html?channel=beinid3",
        "label": "HD AUTO"
      },
      {
        "key": "qcUHOVN5p5",
        "url": "https://bikinbaru96.blogspot.com/p/playermpd.html?channel=daznde2",
        "label": "HD AUTO"
      },
      {
        "key": "CaHUwXOSuf",
        "url": "https://sport.inplaynet.tech/livestream.html?src=aHR0cHM6Ly9zbWQuc3BvcnRwbGF5ZXIuaW8vZW1iZWQucGhwLz9tYXRjaF9pZD0xMjY1OTAwOCZzaz0xYzlhYzAxJnR5cGU9cw==",
        "label": "SD [IOS]"
      },
      {
        "key": "6pxLmNxfAy",
        "url": "https://rr4---sn-8pxuuxa-on.applecdnstore.com/livetv/2024/live_event_espn_plus_13/index.m3u8",
        "label": "SD [IOS]"
      },
      {
        "key": "GJRoIzu5g0",
        "url": "https://kc.elutuna.workers.dev/210/playlist.m3u8",
        "label": "SD [IOS]"
      },
      {
        "key": "mJJt1OL0HP",
        "url": "",
        "label": ""
      }
    ]
  },
  {
    "id": "6f5f1c09-307a-4777-b9aa-a5dc6558a7ae",
    "servers": [
      {
        "key": "8swmjHS420",
        "url": "https://sport.inplaynet.tech/livestream.html?src=aHR0cHM6Ly9zbWQuc3BvcnRwbGF5ZXIuaW8vZW1iZWQucGhwLz9tYXRjaF9pZD0xMjY1ODk4NCZzaz0xYzlhYzAxJnR5cGU9cw==",
        "label": "SD [IOS]"
      },
      {
        "key": "vwbkvgjiG9",
        "url": "https://rr4---sn-8pxuuxa-onon.applecdnstore.com/livetv/2024/live_event_espn_plus_30/index.m3u8",
        "label": "SD [IOS]"
      },
      {
        "key": "ZsIY2S2EfN",
        "url": "",
        "label": ""
      }
    ]
  },
  {
    "id": "5f5141b4-39da-4bf4-8fad-ed823b3c077b",
    "servers": [
      {
        "key": "HsUhOYoJ7J",
        "url": "https://sport.inplaynet.tech/livestream.html?src=aHR0cHM6Ly9zbWQuc3BvcnRwbGF5ZXIuaW8vZW1iZWQucGhwLz9tYXRjaF9pZD0xMjY1ODk5NCZzaz0xYzlhYzAxJnR5cGU9cw==",
        "label": "SD [IOS]"
      },
      {
        "key": "6tq1ekdmUX",
        "url": "https://rr4---sn-8pxuuxa-onon.applecdnstore.com/livetv/2024/live_event_espn_plus_33/index.m3u8",
        "label": "SD [IOS]"
      },
      {
        "key": "5waQbbj6To",
        "url": "",
        "label": ""
      }
    ]
  },
  {
    "id": "01569731-5d5a-4832-9bf2-35c40029d990",
    "servers": [
      {
        "key": "ozFmvq7tUK",
        "url": "https://sport.inplaynet.tech/livestream.html?src=aHR0cHM6Ly9zbWQuc3BvcnRwbGF5ZXIuaW8vZW1iZWQucGhwLz9tYXRjaF9pZD0xMjY1ODk5OCZzaz0xYzlhYzAxJnR5cGU9cw==",
        "label": "SD [IOS]"
      },
      {
        "key": "0Ne5vJxvqa",
        "url": "https://rr4---sn-8pxuuxa-onon.applecdnstore.com/livetv/2024/live_event_espn_plus_28/index.m3u8",
        "label": "SD [IOS]"
      },
      {
        "key": "GiUyxho4WR",
        "url": "",
        "label": ""
      }
    ]
  },
  {
    "id": "c3af8280-f9cb-46c5-810c-ccb37a240c2d",
    "servers": [
      {
        "key": "gZwMAx2WcI",
        "url": "https://bikinbaru96.blogspot.com/p/playermpd.html?channel=arena10cr",
        "label": "HD AUTO"
      },
      {
        "key": "oJ7KKUO9BT",
        "url": "https://sport.inplaynet.tech/livestream.html?src=aHR0cHM6Ly9zbWQuc3BvcnRwbGF5ZXIuaW8vZW1iZWQucGhwLz9tYXRjaF9pZD0xMjY1ODk3MiZzaz0xYzlhYzAxJnR5cGU9cw==",
        "label": "SD [IOS]"
      },
      {
        "key": "GwUrqwPSJj",
        "url": "https://rr4---sn-8pxuuxa-onon.applecdnstore.com/livetv/2024/live_event_espn_plus_31/index.m3u8",
        "label": "SD [IOS]"
      },
      {
        "key": "72e1gBfYpx",
        "url": "https://kc.elutuna.workers.dev/212/playlist.m3u8",
        "label": "SD [IOS]"
      },
      {
        "key": "xIMg70Yja3",
        "url": "",
        "label": ""
      }
    ]
  },
  {
    "id": "7a4b367d-4efc-4888-9bfc-29a61b2a0079",
    "servers": [
      {
        "key": "CuLb44D4r0",
        "url": "",
        "label": ""
      },
      {
        "key": "bCj5Hba2Vj",
        "url": "",
        "label": ""
      },
      {
        "key": "vhEth2XHfW",
        "url": "",
        "label": ""
      }
    ]
  },
  {
    "id": "a79d3a43-e242-4691-a5f1-e7a091330633",
    "servers": [
      {
        "key": "oXTyXEbT66",
        "url": "https://bikinbaru96.blogspot.com/p/playermpd.html?channel=arena5cr",
        "label": "HD AUTO"
      },
      {
        "key": "zI0GHw91Pt",
        "url": "",
        "label": ""
      },
      {
        "key": "OBwoUYy5Nq",
        "url": "",
        "label": ""
      },
      {
        "key": "cu8hzapMWo",
        "url": "",
        "label": ""
      },
      {
        "key": "wvx8ghTx6b",
        "url": "",
        "label": ""
      },
      {
        "key": "Qasbzrqiw9",
        "url": "",
        "label": ""
      }
    ]
  },
  {
    "id": "2fb2a81c-f57b-4cbf-b2f7-def16d5ba38b",
    "servers": [
      {
        "key": "m9TzyISRVG",
        "url": "",
        "label": ""
      },
      {
        "key": "AM2i0DomlK",
        "url": "",
        "label": ""
      },
      {
        "key": "VB2HWXIodS",
        "url": "",
        "label": ""
      }
    ]
  },
  {
    "id": "4e3ead2c-b054-4c6a-ae8e-bf3759a75eb6",
    "servers": [
      {
        "key": "MmJC1BydNj",
        "url": "",
        "label": ""
      },
      {
        "key": "sJcG1gSwhx",
        "url": "",
        "label": ""
      },
      {
        "key": "jPYV3CnzS3",
        "url": "",
        "label": ""
      }
    ]
  },
  {
    "id": "972ed3df-e235-43a1-b33d-1d783121c8b0",
    "servers": [
      {
        "key": "nfWvowPt2k",
        "url": "",
        "label": ""
      },
      {
        "key": "omXg2r2cK6",
        "url": "",
        "label": ""
      },
      {
        "key": "t5CHEkefPT",
        "url": "",
        "label": ""
      },
      {
        "key": "QzKTxrHTnp",
        "url": "",
        "label": ""
      },
      {
        "key": "BmFARY2hue",
        "url": "",
        "label": ""
      },
      {
        "key": "9w3CCorpnG",
        "url": "",
        "label": ""
      }
    ]
  },
  {
    "id": "abb5a3aa-b8e9-4de3-b647-653e1405552f",
    "servers": [
      {
        "key": "AqjI2NeKvo",
        "url": "",
        "label": ""
      },
      {
        "key": "M4slq4w4yn",
        "url": "",
        "label": ""
      },
      {
        "key": "Di3b97PtJY",
        "url": "",
        "label": ""
      }
    ]
  },
  {
    "id": "1982c502-e8e6-4191-96ed-b2d6b8a64293",
    "servers": [
      {
        "key": "srVQyCSw9j",
        "url": "",
        "label": ""
      },
      {
        "key": "mPP7Is04Bc",
        "url": "",
        "label": ""
      },
      {
        "key": "E59GqcfE2L",
        "url": "",
        "label": ""
      }
    ]
  },
  {
    "id": "d55bdf6b-3b81-46b9-ad58-c5ca3df3a385",
    "servers": [
      {
        "key": "bI5kFjuJYV",
        "url": "",
        "label": ""
      },
      {
        "key": "LzidESh7gC",
        "url": "",
        "label": ""
      },
      {
        "key": "GYBpI2kDZu",
        "url": "",
        "label": ""
      }
    ]
  },
  {
    "id": "644173e8-0eaf-4a3e-835b-763aadde00b1",
    "servers": [
      {
        "key": "N783mvtpYR",
        "url": "",
        "label": ""
      },
      {
        "key": "3qrCavf4og",
        "url": "",
        "label": ""
      },
      {
        "key": "MiGEYHem1F",
        "url": "",
        "label": ""
      }
    ]
  }
]